ddsimca/__init__.py
ddsimca/ddsimca.py
ddsimca-1.0.3.dist-info/METADATA
ddsimca-1.0.3.dist-info/WHEEL
ddsimca-1.0.3.dist-info/licenses/LICENSE
ddsimca-1.0.3.dist-info/RECORD
