Metadata-Version: 2.4
Name: ddsimca
Version: 1.0.3
Summary: Implementation of Data Driven SIMCA one class classification method
Project-URL: Homepage, https://github.com/svkucheryavski/ddsimca
Project-URL: Documentation, https://github.com/svkucheryavski/ddsimca
Project-URL: Repository, https://github.com/svkucheryavski/ddsimca
Project-URL: Bug Tracker, https://github.com/svkucheryavski/ddsimca/issues
Author-email: Sergey Kucheryavskiy <svkucheryavski@gmail.com>
License: MIT
License-File: LICENSE
Keywords: anomaly-detection,chemometrics,ddsimca,one-class-classification,simca
Classifier: Development Status :: 4 - Beta
Classifier: Intended Audience :: Science/Research
Classifier: License :: OSI Approved :: MIT License
Classifier: Operating System :: OS Independent
Classifier: Programming Language :: Python :: 3
Classifier: Programming Language :: Python :: 3.8
Classifier: Programming Language :: Python :: 3.9
Classifier: Programming Language :: Python :: 3.10
Classifier: Programming Language :: Python :: 3.11
Classifier: Programming Language :: Python :: 3.12
Classifier: Topic :: Scientific/Engineering :: Artificial Intelligence
Requires-Python: >=3.8
Requires-Dist: matplotlib>=3.8.0
Requires-Dist: numpy>=1.19.0
Requires-Dist: pandas>=2.2.0
Requires-Dist: prcv>1.2.0
Requires-Dist: scipy>=1.6.0
Provides-Extra: dev
Requires-Dist: pytest>=7.0.0; extra == 'dev'
